modeldict/__init__.py
modeldict/base.py
modeldict/models.py
modeldict/redis.py
tests/testapp/__init__.py
tests/testapp/models.py
tests/testapp/test_base.py
tests/testapp/test_modeldict.py
django_modeldict_yplan-2.0.3.dist-info/LICENSE
django_modeldict_yplan-2.0.3.dist-info/METADATA
django_modeldict_yplan-2.0.3.dist-info/WHEEL
django_modeldict_yplan-2.0.3.dist-info/top_level.txt
django_modeldict_yplan-2.0.3.dist-info/RECORD
